another/__init__.py
another/another.py
another/request.py
another/response.py
another/status.py
another-0.2.2.dist-info/LICENSE
another-0.2.2.dist-info/METADATA
another-0.2.2.dist-info/WHEEL
another-0.2.2.dist-info/RECORD
