Metadata-Version: 2.1
Name: another
Version: 0.2.2
Summary: 
Author: Vahid Al
Author-email: thevahidal@gmail.com
Requires-Python: >=3.10,<4.0
Classifier: Programming Language :: Python :: 3
Classifier: Programming Language :: Python :: 3.10
Classifier: Programming Language :: Python :: 3.11
